pht/__init__.py
pht/analysis/__init__.py
pht/analysis/filterwords.py
pht/analysis/verbsremover.py
pht/prefixes_suffixes/PrefixesManager.py
pht/prefixes_suffixes/SuffixesManager.py
pht/prefixes_suffixes/__init__.py
pht/tokenizer/SentencesTokenizer.py
pht/tokenizer/TokenizerManager.py
pht/tokenizer/WordsTokenizer.py
pht/tokenizer/__init__.py
nlp_persian_text_tokenize_snd-0.1.1.dist-info/LICENSE
nlp_persian_text_tokenize_snd-0.1.1.dist-info/METADATA
nlp_persian_text_tokenize_snd-0.1.1.dist-info/WHEEL
nlp_persian_text_tokenize_snd-0.1.1.dist-info/top_level.txt
nlp_persian_text_tokenize_snd-0.1.1.dist-info/RECORD
