Metadata-Version: 2.1
Name: nlp_persian_text_tokenize_snd
Version: 0.1.1
Summary: This library is designed to tokenize Persian texts.
Home-page: https://github.com/7cloner/NLP-Persian-Text-Tokenize-SND
Author: Nasser Khaledi
Author-email: foray00227@gmail.com
Classifier: Programming Language :: Python :: 3
Classifier: License :: OSI Approved :: MIT License
Classifier: Operating System :: OS Independent
Requires-Python: >=3.6
License-File: LICENSE
Requires-Dist: nlp-date-normalization-snd
